[
  {
    "entry_number": 1,
    "github_id": 285863560,
    "github_login": "imrenone",
    "github_avatar": "https://avatars.githubusercontent.com/u/285863560?v=4",
    "template_title": "DeFi Dashboard",
    "app_type": "defi-dashboard",
    "pr_number": 7,
    "pr_url": "https://github.com/gitbankio/autogit-hackathon/pull/7",
    "tx_hash": "0xca41b14a74f35601b795cc5d57f0c6dd04bbb98adabda41caafd7a829c273b42",
    "vault_address": "0x93A36cCD8309e1E0b18d67c09DFbD7cD3ec7899D",
    "paid_at": "2026-05-29T04:00:00.000Z"
  },
  {
    "entry_number": 2,
    "github_id": 171657439,
    "github_login": "Qiu-Difeng",
    "github_avatar": "https://avatars.githubusercontent.com/u/171657439?v=4",
    "template_title": "Expense Tracker",
    "app_type": "expense-tracker",
    "pr_number": 9,
    "pr_url": "https://github.com/gitbankio/autogit-hackathon/pull/9",
    "tx_hash": "0x0a42133bf179a435fe017f983391a9671cb97b32591e3e82f4ffbc05fe287039",
    "vault_address": "0xa048Dd1F00df98b86444EAC5C24d89685A21fD75",
    "paid_at": "2026-05-29T06:19:01.605Z"
  },
  {
    "entry_number": 3,
    "github_id": 286581058,
    "github_login": "EthanGitbanker",
    "github_avatar": "https://avatars.githubusercontent.com/u/286581058?v=4",
    "template_title": "Modern Todo List App",
    "app_type": "todo-app",
    "pr_number": 10,
    "pr_url": "https://github.com/gitbankio/autogit-hackathon/pull/10",
    "tx_hash": "0x4d7fdd579a87aad1f366a88cdba98bc3d55c81fec9b29f8a72930ec5c398b6bf",
    "vault_address": "0x9de234fbF2fCE9e311601eDa7F456b13cF3b2cE0",
    "paid_at": "2026-05-29T06:51:35.254Z"
  },
  {
    "entry_number": 4,
    "github_id": 287358100,
    "github_login": "orbithousezkp",
    "github_avatar": "https://avatars.githubusercontent.com/u/287358100?v=4",
    "template_title": "Signed Cycle Explorer",
    "app_type": "signed-cycle-explorer",
    "pr_number": 13,
    "pr_url": "https://github.com/gitbankio/autogit-hackathon/pull/13",
    "tx_hash": "0x992d29c149b0aec672d0694d81aab00e73fd67672f6a0b8a353699a246ac79f8",
    "vault_address": "0xBdF06E3335C3D01eD8DAB71ea5232EAa6ed00Fb2",
    "paid_at": "2026-05-29T07:10:44.658Z"
  },
  {
    "entry_number": 5,
    "github_id": 288861336,
    "github_login": "GitbankTest",
    "github_avatar": "https://avatars.githubusercontent.com/u/288861336?v=4",
    "template_title": "PrivSend — Simple Private Token Transfer",
    "app_type": "privsend",
    "pr_number": 15,
    "pr_url": "https://github.com/gitbankio/autogit-hackathon/pull/15",
    "tx_hash": "0xbbef3ad646ac648fe611e2aee4943d982d96b9dd27bf07ce404cb63a8f8f5dd8",
    "vault_address": "0x1b2819f7280Ad556d11AD0BA1a335a06c9c42593",
    "paid_at": "2026-05-29T07:26:48.555Z"
  }
]